sanitary/__init__.py
sanitary/hashing.py
sanitary/py.typed
sanitary-0.1.0.dist-info/METADATA
sanitary-0.1.0.dist-info/WHEEL
sanitary-0.1.0.dist-info/licenses/LICENSE.txt
sanitary-0.1.0.dist-info/RECORD
