Metadata-Version: 2.4
Name: sanitary
Version: 0.1.0
Summary: Utility to remove or replace sensitive data from complex structures.
Project-URL: repository, https://github.com/berislavlopac/sanitary
Project-URL: issues, https://github.com/berislavlopac/sanitary/issues
Project-URL: documentation, https://sanitary.readthedocs.io
Author-email: Berislav Lopac <berislav@lopac.net>
License: MIT
License-File: LICENSE.txt
Classifier: Development Status :: 4 - Beta
Classifier: Programming Language :: Python
Classifier: Programming Language :: Python :: 3.8
Classifier: Programming Language :: Python :: 3.9
Classifier: Programming Language :: Python :: 3.10
Classifier: Programming Language :: Python :: 3.11
Classifier: Programming Language :: Python :: Implementation :: CPython
Classifier: Programming Language :: Python :: Implementation :: PyPy
Requires-Python: >=3.10
Provides-Extra: docs
Requires-Dist: jinja2>=3.1.3; extra == 'docs'
Requires-Dist: mkapi; extra == 'docs'
Requires-Dist: mkdocs; extra == 'docs'
Requires-Dist: mkdocs-material; extra == 'docs'
Requires-Dist: pymdown-extensions; extra == 'docs'
